ngboost/__init__.py
ngboost/api.py
ngboost/distns/__init__.py
ngboost/distns/categorical.py
ngboost/distns/cauchy.py
ngboost/distns/distn.py
ngboost/distns/exponential.py
ngboost/distns/gamma.py
ngboost/distns/halfnormal.py
ngboost/distns/laplace.py
ngboost/distns/lognormal.py
ngboost/distns/multivariate_normal.py
ngboost/distns/normal.py
ngboost/distns/poisson.py
ngboost/distns/t.py
ngboost/distns/utils.py
ngboost/distns/weibull.py
ngboost/evaluation.py
ngboost/helpers.py
ngboost/learners.py
ngboost/manifold.py
ngboost/ngboost.py
ngboost/scores.py
ngboost-0.5.7.dist-info/LICENSE
ngboost-0.5.7.dist-info/METADATA
ngboost-0.5.7.dist-info/WHEEL
ngboost-0.5.7.dist-info/RECORD
